hermetic/README.md
hermetic/__about__.py
hermetic/__init__.py
hermetic/__main__.py
hermetic/blocker.py
hermetic/bootstrap.py
hermetic/cli.py
hermetic/errors.py
hermetic/profiles.py
hermetic/resolver.py
hermetic/runner.py
hermetic/util.py
hermetic/guards/__init__.py
hermetic/guards/filesystem.py
hermetic/guards/imports_guard.py
hermetic/guards/network.py
hermetic/guards/subprocess_guard.py
hermetic_seal-0.1.0.dist-info/METADATA
hermetic_seal-0.1.0.dist-info/WHEEL
hermetic_seal-0.1.0.dist-info/entry_points.txt
hermetic_seal-0.1.0.dist-info/licenses/LICENSE
hermetic_seal-0.1.0.dist-info/RECORD
