Metadata-Version: 2.4
Name: hermetic-seal
Version: 0.1.0
Summary: User-space sandbox runner for Python console scripts
Author: Matthew Dean Martin
License-File: LICENSE
Classifier: Development Status :: 1 - Planning
Requires-Python: >=3.9
